postblog/__init__.py
postblog/_web.py
postblog/cli.py
postblog/interface.py
postblog/assets/_postblog.yml
postblog/assets/footer.html.j2
postblog/assets/formcarry.html.j2
postblog/assets/fromcarry.html.j2
postblog/assets/head.html.j2
postblog/assets/index.html.j2
postblog/assets/manifest.json.j2
postblog/assets/nav.html.j2
postblog/assets/news.html.j2
postblog/assets/post.html.j2
postblog/assets/rss.xml.j2
postblog/assets/style.css
postblog/assets/style_font.css
postblog-0.5.2.dist-info/LICENSE
postblog-0.5.2.dist-info/METADATA
postblog-0.5.2.dist-info/WHEEL
postblog-0.5.2.dist-info/entry_points.txt
postblog-0.5.2.dist-info/top_level.txt
postblog-0.5.2.dist-info/RECORD
